MANIFEST.in
README.md
pyproject.toml
setup.py
teramap/__init__.py
teramap/fieldwork.py
teramap/formatters.py
teramap/geojson.py
teramap/utils.py
teramap/views.py
teramap.egg-info/PKG-INFO
teramap.egg-info/SOURCES.txt
teramap.egg-info/dependency_links.txt
teramap.egg-info/top_level.txt
teramap/static/fieldwork.js
teramap/static/index.js
teramap/static/maps.js
teramap/static/debug/fieldwork.html
teramap/static/debug/fieldwork_mapless.html
teramap/static/debug/maps.html
teramap/static/debug/protocols.html
teramap/static/debug/scroll-intent.html
teramap/static/debug/protocols/extra_species.json
teramap/static/debug/protocols/loader.js
teramap/static/debug/protocols/observation.js
teramap/static/debug/protocols/observation_no_pinpoint.js
teramap/static/debug/protocols/observation_no_pinpoint_no_species.js
teramap/static/debug/protocols/observation_remote_species.js
teramap/static/debug/protocols/observation_single_species.js
teramap/static/debug/protocols/observation_single_species_single_subject.js
teramap/static/debug/protocols/sample.js
teramap/static/debug/protocols/sample_more_species.js
teramap/static/debug/protocols/sample_more_species_only_remote.js
teramap/static/debug/protocols/sample_no_pinpoint.js
teramap/static/debug/protocols/sample_subject_collapse.js
teramap/static/debug/protocols/sample_two_groups.js
teramap/static/fieldwork/README.md
teramap/static/fieldwork/fieldwork.css
teramap/static/fieldwork/pinpoint-controller.js
teramap/static/fieldwork/pinpoint-modal.js
teramap/static/fieldwork/pinpoint-table.js
teramap/static/fieldwork/pinpoint.js
teramap/static/fieldwork/protocol.js
teramap/static/fieldwork/species-select.js
teramap/static/fieldwork/utils.js
teramap/static/lib/extend.js
teramap/static/lib/leaflet-number-marker.css
teramap/static/lib/leaflet-number-marker.js
teramap/static/lib/leaflet-scroll-intent.js
teramap/static/lib/template.js
teramap/static/maps/featurelayer.js
teramap/static/maps/layer-bounds.js
teramap/static/maps/leaflet-geojson-map.js
teramap/static/maps/leaflet-map.js
teramap/static/maps/makimarkers.js
teramap/static/maps/simplestyle.js
